s2_pi/__init__.py
s2_pi/s2_pi.py
s2_pi/sbx_to_sb2.py
s2_pi-1.21.dist-info/METADATA
s2_pi-1.21.dist-info/RECORD
s2_pi-1.21.dist-info/WHEEL
s2_pi-1.21.dist-info/entry_points.txt
s2_pi-1.21.dist-info/top_level.txt
