Metadata-Version: 2.1
Name: s2-pi
Version: 1.21
Summary: Creating Scratch 2 Extensions For The Raspberry Pi
Home-page: https://github.com/MrYsLab/s2-pi
Author: Alan Yorinks
Author-email: MisterYsLab@gmail.com
License: GNU General Public License v3 (GPLv3)
Keywords: Raspberry Pi,Scratch 2,Extensions
Platform: UNKNOWN
Classifier: Development Status :: 5 - Production/Stable
Classifier: Environment :: Other Environment
Classifier: Intended Audience :: Education
Classifier: License :: OSI Approved :: GNU General Public License v3 or later (GPLv3+)
Classifier: Operating System :: OS Independent
Classifier: Programming Language :: Python :: 3.4
Classifier: Topic :: Education
Classifier: Topic :: Software Development
